{
"type": "FeatureCollection",
"name": "thedata",
"features": [
{ "type": "Feature", "properties": { }, "geometry": { "type": "LineString", "coordinates": [ [ -75.144207, 40.03869, 0.0 ], [ -75.144679, 40.038771, 0.0 ], [ -75.144254, 40.041091, 0.0 ] ] } },
{ "type": "Feature", "properties": { }, "geometry": { "type": "LineString", "coordinates": [ [ -75.144254, 40.041091, 0.0 ], [ -75.144854, 40.038729, 0.0 ] ] } },
{ "type": "Feature", "properties": { }, "geometry": { "type": "LineString", "coordinates": [ [ -75.144179, 40.041388, 0.0 ], [ -75.144254, 40.041091, 0.0 ] ] } },
{ "type": "Feature", "properties": { }, "geometry": { "type": "LineString", "coordinates": [ [ -75.144179, 40.041388, 0.0 ], [ -75.144421, 40.041747, 0.0 ], [ -75.144438, 40.043751, 0.0 ], [ -75.144627, 40.044562, 0.0 ] ] } },
{ "type": "Feature", "properties": { }, "geometry": { "type": "LineString", "coordinates": [ [ -75.143836, 40.042894, 0.0 ], [ -75.144179, 40.041388, 0.0 ] ] } },
{ "type": "Feature", "properties": { }, "geometry": { "type": "LineString", "coordinates": [ [ -75.143836, 40.042894, 0.0 ], [ -75.142719, 40.042749, 0.0 ], [ -75.143663, 40.038608, 0.0 ] ] } },
{ "type": "Feature", "properties": { }, "geometry": { "type": "LineString", "coordinates": [ [ -75.144627, 40.044562, 0.0 ], [ -75.143512, 40.044421, 0.0 ], [ -75.143836, 40.042894, 0.0 ] ] } },
{ "type": "Feature", "properties": { }, "geometry": { "type": "LineString", "coordinates": [ [ -75.158347, 40.073986, 0.0 ], [ -75.155971, 40.066158, 0.0 ], [ -75.155103, 40.065202, 0.0 ], [ -75.152788, 40.063714, 0.0 ], [ -75.149258, 40.058501, 0.0 ], [ -75.149222, 40.057992, 0.0 ], [ -75.150154, 40.05158, 0.0 ], [ -75.151052, 40.047498, 0.0 ], [ -75.151001, 40.046851, 0.0 ], [ -75.149672, 40.044981, 0.0 ], [ -75.146807, 40.044855, 0.0 ], [ -75.144627, 40.044562, 0.0 ] ] } },
{ "type": "Feature", "properties": { }, "geometry": { "type": "LineString", "coordinates": [ [ -75.158347, 40.073986, 0.0 ], [ -75.158419, 40.074201, 0.0 ] ] } },
{ "type": "Feature", "properties": { }, "geometry": { "type": "LineString", "coordinates": [ [ -75.158419, 40.074201, 0.0 ], [ -75.158347, 40.073986, 0.0 ] ] } },
{ "type": "Feature", "properties": { }, "geometry": { "type": "LineString", "coordinates": [ [ -75.158419, 40.074201, 0.0 ], [ -75.159126, 40.07459, 0.0 ], [ -75.159157, 40.074817, 0.0 ] ] } },
{ "type": "Feature", "properties": { }, "geometry": { "type": "LineString", "coordinates": [ [ -75.159133, 40.074879, 0.0 ], [ -75.158701, 40.074929, 0.0 ], [ -75.158419, 40.074201, 0.0 ] ] } }
]
}
